MANIFEST.in
setup.cfg
setup.py
versioneer.py
test_versioneer_setup_nathanwilk7/__init__.py
test_versioneer_setup_nathanwilk7/_version.py
test_versioneer_setup_nathanwilk7/test_versioneer_setup_file.py
test_versioneer_setup_nathanwilk7.egg-info/PKG-INFO
test_versioneer_setup_nathanwilk7.egg-info/SOURCES.txt
test_versioneer_setup_nathanwilk7.egg-info/dependency_links.txt
test_versioneer_setup_nathanwilk7.egg-info/top_level.txt