Metadata-Version: 1.0
Name: test-versioneer-setup-nathanwilk7
Version: 1.0
Summary: Test with versioneer, setup.py, uploaded to pypi, then to conda, then taggable, etc.
Home-page: UNKNOWN
Author: Recursion Pharmaceuticals
Author-email: dev@recursionpharma.com
License: UNKNOWN
Platform: UNKNOWN
